sphinx_guillotina_theme/__init__.py
sphinx_guillotina_theme/theme/layout.html
sphinx_guillotina_theme/theme/localtoc.html
sphinx_guillotina_theme/theme/relations.html
sphinx_guillotina_theme/theme/search.html
sphinx_guillotina_theme/theme/searchbox.html
sphinx_guillotina_theme/theme/theme.conf
sphinx_guillotina_theme/theme/static/favicon.ico
sphinx_guillotina_theme/theme/static/.sass-cache/23f394738b115016400f62ec1e9f24cf64bab39b/main.scssc
sphinx_guillotina_theme/theme/static/css/basic.css
sphinx_guillotina_theme/theme/static/css/main.css
sphinx_guillotina_theme/theme/static/css/main.scss
sphinx_guillotina_theme/theme/static/css/nature.css
sphinx_guillotina_theme/theme/static/css/pastanaga.css
sphinx_guillotina_theme/theme/static/css/pastanaga.ttf
sphinx_guillotina_theme/theme/static/css/pastanaga.woff
sphinx_guillotina_theme/theme/static/css/.sass-cache/ee3b03fa66ef63d76544d6d6cb0bb25332e030d7/main.scssc
sphinx_guillotina_theme/theme/static/img/logo.png
sphinx_guillotina_theme/theme/static/img/logo.svg
sphinx_guillotina_theme-1.0.9.dist-info/METADATA
sphinx_guillotina_theme-1.0.9.dist-info/WHEEL
sphinx_guillotina_theme-1.0.9.dist-info/top_level.txt
sphinx_guillotina_theme-1.0.9.dist-info/zip-safe
sphinx_guillotina_theme-1.0.9.dist-info/RECORD
