Metadata-Version: 2.4
Name: sphinx-guillotina-theme
Version: 1.0.9
Summary: sphinx theme for guillotina
Home-page: https://github.com/guillotinaweb/sphinx-guillotina-theme
Author: Nathan Van Gheem
Author-email: vangheem@gmail.com
License: BSD
Keywords: sphinx,theme,guillotina
Requires-Dist: sphinx
Dynamic: author
Dynamic: author-email
Dynamic: description
Dynamic: home-page
Dynamic: keywords
Dynamic: license
Dynamic: requires-dist
Dynamic: summary
